[
	{
		"titleId": 1,
		"enChamp": "Aatrox",
		"cnChamp": "厄薩斯",
		"src": "./ChampionImg/AatroxSquare.jpg",
		"author": "dog",
		"title": "title XXX",
		"contentTxt": "123",
		"upTotal": 5,
		"downTotal": 19,
		"titleTime": "subTime"
	},
	{
		"titleId": 2,
		"enChamp": "Ahri",
		"cnChamp": "阿璃",
		"src": "./ChampionImg/AhriSquare.jpg",
		"author": "cat",
		"title": "title B",
		"contentTxt": "asdf12s3",
		"upTotal": 15,
		"downTotal": 119,
		"titleTime": "subTime"
	},
	{
		"titleId": 1699934009695,
		"enChamp": "Akali",
		"cnChamp": "阿卡莉",
		"src": "ChampionImg/AkaliSquare.jpg",
		"author": "Shuan",
		"title": "實驗4",
		"upTotal": 0,
		"downTotal": 0,
		"contentTxt": "<p>實驗4</p>",
		"titleTime": "2023-11-14 11:53"
	},
	{
		"titleId": 1699940071231,
		"enChamp": "Ahri",
		"cnChamp": "阿璃",
		"src": "./ChampionImg/AhriSquare.jpg",
		"author": "Shuan",
		"title": "123",
		"upTotal": 0,
		"downTotal": 0,
		"contentTxt": "<p>4568743</p><p>5</p>",
		"titleTime": "2023-11-14 13:34"
	},
	{
		"titleId": 1699968061678,
		"enChamp": "Aatrox",
		"cnChamp": "厄薩斯",
		"src": "./ChampionImg/AatroxSquare.jpg",
		"author": "123",
		"title": "測試內文",
		"upTotal": 0,
		"downTotal": 0,
		"contentTxt": "<p>123</p><p>11</p><p>2</p><p>2</p><p>32</p><p>31</p><p>5</p><p>1</p><p>5</p><p>15</p><p>4</p><p>4</p><p>4</p><p>&nbsp;</p>",
		"titleTime": "於2023-11-15 01:34 已編輯"
	},
	{
		"titleId": 1699974187770,
		"enChamp": "Ahri",
		"cnChamp": "阿璃",
		"src": "./ChampionImg/AhriSquare.jpg",
		"author": "Shuan",
		"title": "123",
		"upTotal": 0,
		"downTotal": 0,
		"contentTxt": "<p>123456</p><p>&nbsp;</p><p>可用</p>",
		"titleTime": "於2023-11-15 01:42 已編輯"
	},
	{
		"titleId": 1699978524683,
		"enChamp": "Aphelios",
		"cnChamp": "亞菲利歐",
		"src": "ChampionImg/ApheliosSquare.jpg",
		"author": "123",
		"title": "新的測試",
		"upTotal": 0,
		"downTotal": 0,
		"contentTxt": "<p>是否能成功</p>",
		"titleTime": "2023-11-15 00:15"
	},
	{
		"titleId": 1699978725888,
		"enChamp": "Akshan",
		"cnChamp": "埃可尚",
		"src": "ChampionImg/AkshanSquare.jpg",
		"author": "123",
		"title": "在測試",
		"upTotal": 0,
		"downTotal": 0,
		"contentTxt": "<p>成功嗎</p>",
		"titleTime": "2023-11-15 00:18"
	},
	{
		"titleId": 1699978786092,
		"enChamp": "Akshan",
		"cnChamp": "埃可尚",
		"src": "ChampionImg/AkshanSquare.jpg",
		"author": "123",
		"title": "在測試",
		"upTotal": 0,
		"downTotal": 0,
		"contentTxt": "<p>成功嗎</p>",
		"titleTime": "2023-11-15 00:19"
	},
	{
		"titleId": 1699978854497,
		"enChamp": "Akshan",
		"cnChamp": "埃可尚",
		"src": "ChampionImg/AkshanSquare.jpg",
		"author": "123",
		"title": "成功嗎",
		"upTotal": 0,
		"downTotal": 0,
		"titleTime": "2023-11-15 00:20"
	},
	{
		"titleId": 1699978856059,
		"enChamp": "Akshan",
		"cnChamp": "埃可尚",
		"src": "ChampionImg/AkshanSquare.jpg",
		"author": "123",
		"title": "成功嗎",
		"upTotal": 0,
		"downTotal": 0,
		"titleTime": "2023-11-15 00:20"
	},
	{
		"titleId": 1699978920127,
		"enChamp": "Ahri",
		"cnChamp": "阿璃",
		"src": "ChampionImg/AhriSquare.jpg",
		"author": "123",
		"title": "123",
		"upTotal": 0,
		"downTotal": 0,
		"contentTxt": "<p>456</p>",
		"titleTime": "2023-11-15 00:22"
	},
	{
		"titleId": 1699978935759,
		"enChamp": "Aatrox",
		"cnChamp": "厄薩斯",
		"src": "ChampionImg/AatroxSquare.jpg",
		"author": "123",
		"title": "我回歸了",
		"upTotal": 0,
		"downTotal": 0,
		"contentTxt": "<p>歸剛ㄟ</p>",
		"titleTime": "2023-11-15 00:22"
	},
	{
		"titleId": 1700028067442,
		"enChamp": "Ahri",
		"cnChamp": "阿璃",
		"src": "ChampionImg/AhriSquare.jpg",
		"author": "Shuan",
		"title": "修正",
		"upTotal": 0,
		"downTotal": 0,
		"contentTxt": "<p>123</p>",
		"titleTime": "2023-11-15 14:01"
	},
	{
		"titleId": 1700028222834,
		"enChamp": "Ahri",
		"cnChamp": "阿璃",
		"src": "./ChampionImg/AhriSquare.jpg",
		"author": "Shuan",
		"title": "功能型英雄也能當輸出",
		"upTotal": 0,
		"downTotal": 0,
		"contentTxt": "<p>這個角色的定位通常是控場</p><p>但是在低牌位這個特性變成劣勢</p><p>在出裝上就要做大幅度的調整</p><p>&nbsp;</p>",
		"titleTime": "於2023-11-15 14:10 已編輯"
	},
	{
		"titleId": 1700067778785,
		"enChamp": "Draven",
		"cnChamp": "達瑞文",
		"src": "ChampionImg/DravenSquare.jpg",
		"author": "Shuan",
		"title": "測試",
		"upTotal": 0,
		"downTotal": 0,
		"contentTxt": "<p>DEMO</p>",
		"titleTime": "2023-11-16 01:02"
	}
]